strong_password/__init__.py
strong_password/generator.py
pyaoponto_password-0.1.0.dist-info/entry_points.txt
pyaoponto_password-0.1.0.dist-info/METADATA
pyaoponto_password-0.1.0.dist-info/WHEEL
pyaoponto_password-0.1.0.dist-info/RECORD
